pi_touch_gui/__init__.py
pi_touch_gui/_utilities.py
pi_touch_gui/_widget_bases.py
pi_touch_gui/colors.py
pi_touch_gui/function_registry.py
pi_touch_gui/gui.py
pi_touch_gui/page.py
pi_touch_gui/widget_buttons.py
pi_touch_gui/widget_controls.py
pi_touch_gui/widget_displays.py
pi_touch_gui/widget_functions.py
pi_touch_gui/Pimoroni/__init__.py
pi_touch_gui/Pimoroni/hp4ts.py
pi_touch_gui/assets/lcars_screen.png
pi_touch_gui/multitouch/__init__.py
pi_touch_gui/multitouch/raspberrypi_ts.py
tests/__init__.py
tests/_utilities.py
tests/manual_touch_test.py
tests/test_pages/__init__.py
tests/test_pages/entry_page.py
tests/test_pages/pages.py
tests/test_pages/poweroff_page.py
tests/test_pages/sampler_page.py
pi_touch_gui-0.3.10.dist-info/LICENSE
pi_touch_gui-0.3.10.dist-info/METADATA
pi_touch_gui-0.3.10.dist-info/WHEEL
pi_touch_gui-0.3.10.dist-info/top_level.txt
pi_touch_gui-0.3.10.dist-info/RECORD
