Metadata-Version: 2.1
Name: pi-touch-gui
Version: 0.3.10
Summary: A graphic UI optimized for touch screens
Home-page: https://github.com/EdwinWiseOne/PiTouchGui
Author: Edwin Wise
Author-email: edwin@simreal.com
License: UNKNOWN
Platform: UNKNOWN
Classifier: Development Status :: 3 - Alpha
Classifier: Intended Audience :: Developers
Classifier: License :: Free for non-commercial use
Classifier: Programming Language :: Python :: 3 :: Only
Classifier: Topic :: Home Automation
Classifier: Topic :: Software Development :: Libraries
Requires-Python: >=3.6
Requires-Dist: pygame
